LICENSE
MANIFEST.in
README.md
setup.py
Paling.egg-info/PKG-INFO
Paling.egg-info/SOURCES.txt
Paling.egg-info/dependency_links.txt
Paling.egg-info/requires.txt
Paling.egg-info/top_level.txt
paling/__init__.py
paling/__main__.py
paling/browsers.py
paling/chrome.py
paling/edge.py
paling/electron.py
paling/paling.js
paling/py.typed
paling/types.py