Metadata-Version: 2.1
Name: Paling
Version: 0.16.3
Summary: For little HTML GUI applications, with easy Python/JS interop
Home-page: https://github.com/python-paling/Paling
Author: OpenSource Team - Roborian
Author-email: info@roborian.com
License: MIT
Keywords: gui,html,javascript,electron
Classifier: Development Status :: 3 - Alpha
Classifier: Natural Language :: English
Classifier: Operating System :: MacOS
Classifier: Operating System :: POSIX
Classifier: Operating System :: Microsoft :: Windows :: Windows 10
Classifier: Programming Language :: Python :: 3
Classifier: Programming Language :: Python :: 3.8
Classifier: Programming Language :: Python :: 3.9
Classifier: Programming Language :: Python :: 3.10
Classifier: Programming Language :: Python :: 3.11
Classifier: Programming Language :: Python :: 3.12
Classifier: Programming Language :: Python :: Implementation :: CPython
Classifier: License :: OSI Approved :: MIT License
Requires-Python: >=3.7
License-File: LICENSE
Requires-Dist: bottle
Requires-Dist: bottle-websocket
Requires-Dist: future
Requires-Dist: pyparsing
Requires-Dist: whichcraft
Provides-Extra: jinja2
Requires-Dist: jinja2>=2.10; extra == "jinja2"
